diffgpt/__init__.py
diffgpt/cli.py
diffgpt-0.2.1.dist-info/METADATA
diffgpt-0.2.1.dist-info/WHEEL
diffgpt-0.2.1.dist-info/entry_points.txt
diffgpt-0.2.1.dist-info/RECORD
