Metadata-Version: 2.4
Name: diffgpt
Version: 0.2.1
Summary: Add your description here
Author-email: Tony Okeke <tonykabilanokeke@gmail.com>
Requires-Python: >=3.11
Requires-Dist: click>=8.1.7
Requires-Dist: openai>=1.57.3
Requires-Dist: pydantic>=2.10.3
